graph2mat/CMakeLists.txt
graph2mat/__init__.py
graph2mat/__version__.py
graph2mat/conftest.py
graph2mat/bindings/__init__.py
graph2mat/bindings/e3nn/__init__.py
graph2mat/bindings/e3nn/irreps_tools.py
graph2mat/bindings/e3nn/_stored_rtps/__init__.py
graph2mat/bindings/e3nn/_stored_rtps/_gen_rtps.py
graph2mat/bindings/e3nn/_stored_rtps/_stored_rtps.py
graph2mat/bindings/e3nn/modules/__init__.py
graph2mat/bindings/e3nn/modules/_utils.py
graph2mat/bindings/e3nn/modules/edge_operations.py
graph2mat/bindings/e3nn/modules/graph2mat.py
graph2mat/bindings/e3nn/modules/matrixblock.py
graph2mat/bindings/e3nn/modules/node_operations.py
graph2mat/bindings/e3nn/modules/preprocessing.py
graph2mat/bindings/e3nn/modules/tests/test_e3nngraph2mat.py
graph2mat/bindings/e3nn/tests/test_rtps.py
graph2mat/bindings/torch/__init__.py
graph2mat/bindings/torch/conftest.py
graph2mat/bindings/torch/load.py
graph2mat/bindings/torch/data/__init__.py
graph2mat/bindings/torch/data/data.py
graph2mat/bindings/torch/data/dataset.py
graph2mat/bindings/torch/data/formats.py
graph2mat/bindings/torch/data/tests/test_data.py
graph2mat/bindings/torch/modules/__init__.py
graph2mat/bindings/torch/modules/graph2mat.py
graph2mat/bindings/torch/modules/matrixblock.py
graph2mat/bindings/torch/modules/tests/test_basis_matrix.py
graph2mat/bindings/torch/tests/test_orbital_matrix.py
graph2mat/core/CMakeLists.txt
graph2mat/core/__init__.py
graph2mat/core/_docstrings.py
graph2mat/core/data/CMakeLists.txt
graph2mat/core/data/__init__.py
graph2mat/core/data/_sparse.cpython-39-x86_64-linux-gnu.so
graph2mat/core/data/_sparse.py
graph2mat/core/data/basis.py
graph2mat/core/data/configuration.py
graph2mat/core/data/formats.py
graph2mat/core/data/metrics.py
graph2mat/core/data/neighborhood.py
graph2mat/core/data/node_feats.py
graph2mat/core/data/processing.py
graph2mat/core/data/sparse.py
graph2mat/core/data/table.py
graph2mat/core/data/matrices/__init__.py
graph2mat-0.0.13.dist-info/METADATA
graph2mat-0.0.13.dist-info/WHEEL
graph2mat-0.0.13.dist-info/entry_points.txt
graph2mat-0.0.13.dist-info/RECORD
graph2mat-0.0.13.dist-info/licenses/LICENSE
