Metadata-Version: 2.2
Name: graph2mat
Version: 0.0.13
Summary: Utility package to work with equivariant matrices and graphs.
Keywords: machine learning,equivariance,e3nn,matrix
Author-Email: Pol Febrer <pfebrer96@gmail.com>, =?utf-8?q?Peter_B=2E_J=C3=B8rgensen?= <peterbjorgensen@gmail.com>
License: MIT
Classifier: Programming Language :: Python :: 3.9
Classifier: Programming Language :: Python :: 3.10
Classifier: Programming Language :: Python :: 3.11
Classifier: Programming Language :: Python :: 3.12
Classifier: Topic :: Scientific/Engineering
Requires-Python: >=3.9
Requires-Dist: numpy
Requires-Dist: scipy
Requires-Dist: ase
Requires-Dist: sisl[viz]>=0.15.0
Requires-Dist: typer
Provides-Extra: server
Requires-Dist: pyyaml; extra == "server"
Requires-Dist: fastapi; extra == "server"
Requires-Dist: uvicorn; extra == "server"
Requires-Dist: python-multipart; extra == "server"
Requires-Dist: jinja2; extra == "server"
Provides-Extra: analysis
Requires-Dist: plotly; extra == "analysis"
Requires-Dist: pandas; extra == "analysis"
Provides-Extra: lightning
Requires-Dist: pytorch-lightning; extra == "lightning"
Requires-Dist: jsonargparse[signatures]; extra == "lightning"
Requires-Dist: tensorboard; extra == "lightning"
Provides-Extra: siesta
Requires-Dist: jinja2; extra == "siesta"
Provides-Extra: torch
Requires-Dist: torch; extra == "torch"
Requires-Dist: torch_geometric; extra == "torch"
Provides-Extra: e3nn
Requires-Dist: torch; extra == "e3nn"
Requires-Dist: torch_geometric; extra == "e3nn"
Requires-Dist: e3nn; extra == "e3nn"
Provides-Extra: mace
Requires-Dist: torch; extra == "mace"
Requires-Dist: torch_geometric; extra == "mace"
Requires-Dist: mace_torch; extra == "mace"
Provides-Extra: tools
Requires-Dist: pyyaml; extra == "tools"
Requires-Dist: fastapi; extra == "tools"
Requires-Dist: uvicorn; extra == "tools"
Requires-Dist: python-multipart; extra == "tools"
Requires-Dist: plotly; extra == "tools"
Requires-Dist: kaleido; extra == "tools"
Requires-Dist: pandas; extra == "tools"
Requires-Dist: pytorch-lightning; extra == "tools"
Requires-Dist: jsonargparse[signatures]; extra == "tools"
Requires-Dist: jinja2; extra == "tools"
Requires-Dist: mace_torch; extra == "tools"
Requires-Dist: tensorboard; extra == "tools"
Provides-Extra: docs
Requires-Dist: pyyaml; extra == "docs"
Requires-Dist: fastapi; extra == "docs"
Requires-Dist: uvicorn; extra == "docs"
Requires-Dist: plotly>6; extra == "docs"
Requires-Dist: pandas; extra == "docs"
Requires-Dist: pytorch-lightning; extra == "docs"
Requires-Dist: jsonargparse[signatures]; extra == "docs"
Requires-Dist: jinja2; extra == "docs"
Requires-Dist: sphinx; extra == "docs"
Requires-Dist: sphinx-copybutton; extra == "docs"
Requires-Dist: sphinx_autodoc_typehints; extra == "docs"
Requires-Dist: sphinx_rtd_theme; extra == "docs"
Requires-Dist: nbsphinx; extra == "docs"
Requires-Dist: ipykernel; extra == "docs"
Requires-Dist: torch; extra == "docs"
Requires-Dist: e3nn>=0.5.0; extra == "docs"
Requires-Dist: torch_geometric; extra == "docs"
Provides-Extra: test
Requires-Dist: pytest; extra == "test"
Requires-Dist: pyyaml; extra == "test"
Requires-Dist: plotly; extra == "test"
Requires-Dist: pandas; extra == "test"
Requires-Dist: pytorch-lightning; extra == "test"
Requires-Dist: e3nn; extra == "test"
Requires-Dist: torch; extra == "test"
Requires-Dist: mace_torch; extra == "test"
Requires-Dist: torch_geometric; extra == "test"
Requires-Dist: jsonargparse[signatures]; extra == "test"
Requires-Dist: jinja2; extra == "test"
